wolfpackutil/__init__.py
wolfpackutil/util.py
wolfpackutil-0.1.7.dist-info/METADATA
wolfpackutil-0.1.7.dist-info/WHEEL
wolfpackutil-0.1.7.dist-info/top_level.txt
wolfpackutil-0.1.7.dist-info/RECORD
