Metadata-Version: 2.1
Name: wolfpackutil
Version: 0.1.7
Summary: Python util library for WolfpackMC packages. https://github.com/WolfpackMC
Home-page: https://github.com/WolfpackMC/wolfpackutil
Author: Kalka
Author-email: kalka2088@gmail.com
License: UNKNOWN
Project-URL: Bug Tracker, https://github.com/WolfpackMC/wolfpackutil/issues
Platform: UNKNOWN
Requires-Python: >=3.10
Requires-Dist: owoify-py
Requires-Dist: pyfiglet
Requires-Dist: python-dateutil
Requires-Dist: rich
Requires-Dist: tinydb
Requires-Dist: appdirs
Requires-Dist: requests
